andebox/__init__.py
andebox/__main__.py
andebox/actions/__init__.py
andebox/actions/ansibletest.py
andebox/actions/base.py
andebox/actions/context.py
andebox/actions/docsite.py
andebox/actions/ignorefile.py
andebox/actions/runtime.py
andebox/actions/toxtest.py
andebox/actions/vagrant.py
andebox/actions/yaml_doc.py
andebox/cli.py
andebox/context.py
andebox/exceptions.py
andebox-1.9.0.dist-info/METADATA
andebox-1.9.0.dist-info/WHEEL
andebox-1.9.0.dist-info/entry_points.txt
andebox-1.9.0.dist-info/licenses/LICENSES/MIT.txt
andebox-1.9.0.dist-info/RECORD
