Metadata-Version: 2.4
Name: andebox
Version: 1.9.0
Summary: Ansible Developers Box
License: MIT
License-File: LICENSES/MIT.txt
Keywords: ansible,tox,vagrant
Author: Alexei Znamensky
Author-email: russoz@gmail.com
Requires-Python: >=3.11,<4.0
Classifier: Development Status :: 4 - Beta
Classifier: Environment :: Console
Classifier: Framework :: Ansible
Classifier: Intended Audience :: Developers
Classifier: Intended Audience :: Information Technology
Classifier: Intended Audience :: System Administrators
Classifier: License :: OSI Approved :: MIT License
Classifier: Operating System :: OS Independent
Classifier: Programming Language :: Python
Classifier: Programming Language :: Python :: 3
Classifier: Programming Language :: Python :: 3.11
Classifier: Programming Language :: Python :: 3.12
Classifier: Programming Language :: Python :: 3.13
Classifier: Programming Language :: Python :: 3.14
Classifier: Topic :: Software Development :: Testing
Classifier: Topic :: Utilities
Requires-Dist: ansible-core (>=2.15.0,<3.0.0) ; python_version == "3.11"
Requires-Dist: ansible-core (>=2.17.4) ; python_version >= "3.12"
Requires-Dist: antsibull-docs (>=2.16.3)
Requires-Dist: argcomplete (>=3.5.3)
Requires-Dist: fabric (>=3.1.0)
Requires-Dist: python-vagrant (>=1.0.0)
Requires-Dist: pyyaml (>=5.4)
Requires-Dist: ruamel-yaml (>=0.18.6,!=0.18.13,!=0.18.14)
Requires-Dist: tox (>=4.5.2)
Project-URL: Bug Tracker, https://github.com/russoz-ansible/andebox/issues
Project-URL: Changelog, https://github.com/russoz-ansible/andebox/blob/main/CHANGELOG.md
Project-URL: Documentation, https://andebox.readthedocs.io/en/latest/index.html
Project-URL: Homepage, https://github.com/russoz-ansible/andebox
Project-URL: Repository, https://github.com/russoz-ansible/andebox
Project-URL: Source Code, https://github.com/russoz-ansible/andebox
